pyroll/pillar_model/__init__.py
pyroll/pillar_model/profile.py
pyroll/pillar_model/report.py
pyroll/pillar_model/roll_pass/__init__.py
pyroll/pillar_model/roll_pass/pillar_disk_element.py
pyroll/pillar_model/roll_pass/roll_pass.py
pyroll/pillar_model/roll_pass/hookimpls/__init__.py
pyroll/pillar_model/roll_pass/hookimpls/pillar_disk_element.py
pyroll/pillar_model/roll_pass/hookimpls/profile.py
pyroll/pillar_model/roll_pass/hookimpls/roll.py
pyroll/pillar_model/roll_pass/hookimpls/roll_pass.py
pyroll_pillar_model-3.0.3.dist-info/METADATA
pyroll_pillar_model-3.0.3.dist-info/WHEEL
pyroll_pillar_model-3.0.3.dist-info/licenses/LICENSE
pyroll_pillar_model-3.0.3.dist-info/RECORD
