Metadata-Version: 2.4
Name: pyroll-pillar-model
Version: 3.0.3
Summary: Plugin for PyRolL providing basic data structures for discretization of a Profile and a RollPass into Pillar Elements. 
Author-email: Max Weiner <max.weiner@imf.tu-freiberg.de>, Christoph Renzing <christoph.renzing@imf.tu-freiberg.de>
License-Expression: BSD-3-Clause
License-File: LICENSE
Requires-Python: <4.0,>=3.9
Requires-Dist: more-itertools~=9.0
Requires-Dist: plotly
Requires-Dist: pyroll-core~=3.0
